windows_fsm/window_fsm.v
module window_fsm
    (
        input   wire button_press, n_reset, clk,
        output  reg open_cw, close_ccw
    );

    localparam  STATE_CLOSED = 1'b0,
                STATE_OPENED = 1'b1;

    reg next_state = STATE_CLOSED;
    reg current_state = STATE_CLOSED;

    //next state logic
    always @(current_state, button_press) begin
        case(current_state)
            STATE_CLOSED:
                if(button_press == 1'b0) begin
                    next_state = STATE_CLOSED;
                end else begin
                    next_state = STATE_OPENED;
                end
            STATE_OPENED:
                if(button_press == 1'b0) begin
                    next_state = STATE_OPENED;
                end else begin
                    next_state = STATE_CLOSED;
                end
        endcase
    end

    //output logic
    always @(current_state, button_press) begin
        case(current_state)
            STATE_CLOSED:
                if(button_press == 1'b0) begin
                    close_ccw = 1'b0;
                    open_cw = 1'b0;
                end else begin
                    close_ccw = 1'b0;
                    open_cw = 1'b1;
                end
            STATE_OPENED:
                if(button_press == 1'b0) begin
                    open_cw = 1'b0;
                    close_ccw = 1'b0;
                end else begin
                    open_cw = 1'b0;
                    close_ccw = 1'b1;
                end
        endcase
    end

    //current state logic
    always @(posedge clk) begin
        if (n_reset == 0) begin
            current_state <= STATE_CLOSED;
        end else begin
            current_state <= next_state;
        end
    end

endmodule

windows_fsm/window_fsm_tb.v
`include "window_fsm.v"
`timescale 1us/1ns

module window_fsm_tb;
    reg button_press = 1'b0;
    reg n_reset = 1'b0;
    reg clk = 1'b0;

    window_fsm dut
    (
        .button_press(button_press),
        .n_reset(n_reset),
        .clk(clk)
    );

    initial begin
        $dumpfile("window_fsm.vcd");
        $dumpvars(0, window_fsm_tb);
    end

    initial begin
        forever begin
            #10
            clk = ~clk;
        end
    end

    initial begin
        #56
        n_reset <= 1'b1;
        #14
        button_press <= 1'b1;
        #46
        button_press <= 1'b0;
        #22
        button_press <= 1'b1;
        #1
        button_press <= 1'b0;
        #10
        n_reset <= 1'b0;
        #22
        button_press <= 1'b1;
        #66
        button_press <= 1'b0;
        #10
        $display("Test Complete");
        $finish;
    end

endmodule

windows_fsm/window_fsm.vcd
$date
	Mon Jul 31 12:03:30 2023
$end
$version
	Icarus Verilog
$end
$timescale
	1ns
$end
$scope module window_fsm_tb $end
$var reg 1 ! button_press $end
$var reg 1 " clk $end
$var reg 1 # n_reset $end
$scope module dut $end
$var wire 1 ! button_press $end
$var wire 1 " clk $end
$var wire 1 # n_reset $end
$var reg 1 $ close_ccw $end
$var reg 1 % current_state $end
$var reg 1 & next_state $end
$var reg 1 ' open_cw $end
$upscope $end
$upscope $end
$enddefinitions $end
#0
$dumpvars
0'
0&
0%
0$
0#
0"
0!
$end
#10000
1"
#20000
0"
#30000
1"
#40000
0"
#50000
1"
#56000
1#
#60000
0"
#70000
1&
1'
1!
1"
#80000
0"
#90000
1$
0'
0&
1%
1"
#100000
0"
#110000
1&
1'
0$
0%
1"
#116000
0'
0&
0!
#120000
0"
#130000
1"
#138000
1&
1'
1!
#139000
0'
0&
0!
#140000
0"
#149000
0#
#150000
1"
#160000
0"
#170000
1"
#171000
1&
1'
1!
#180000
0"
#190000
1"
#200000
0"
#210000
1"
#220000
0"
#230000
1"
#237000
0'
0&
0!
